doormouse/__init__.py
doormouse/cli.py
doormouse/conf.py
doormouse/datastore.py
doormouse/filestore.py
doormouse/x509.py
doormouse-1.1.0.dist-info/DESCRIPTION.rst
doormouse-1.1.0.dist-info/METADATA
doormouse-1.1.0.dist-info/RECORD
doormouse-1.1.0.dist-info/WHEEL
doormouse-1.1.0.dist-info/entry_points.txt
doormouse-1.1.0.dist-info/metadata.json
doormouse-1.1.0.dist-info/top_level.txt
tests/__init__.py
tests/performance.py
tests/test_cli.py
tests/test_conf.py
tests/test_datastore.py
tests/test_doormouse.py
tests/test_filestore.py
tests/test_x509.py
