Metadata-Version: 2.0
Name: doormouse
Version: 1.1.0
Summary: PKI without the PITA.
Home-page: http://github.com/doormouseio/doormouse-core
Author: BrainGu
Author-email: doormouse@braingu.com
License: Apache Software License
Keywords: x509 ca certificate pki doormouse openssl
Platform: UNKNOWN
Classifier: Development Status :: 5 - Production/Stable
Classifier: Environment :: Console
Classifier: Intended Audience :: Developers
Classifier: Intended Audience :: Information Technology
Classifier: Intended Audience :: System Administrators
Classifier: License :: OSI Approved :: Apache Software License
Classifier: Natural Language :: English
Classifier: Operating System :: MacOS :: MacOS X
Classifier: Operating System :: Microsoft :: Windows :: Windows 7
Classifier: Operating System :: POSIX :: Linux
Classifier: Programming Language :: Python :: 2.7
Classifier: Topic :: Security
Classifier: Topic :: Security :: Cryptography
Classifier: Topic :: Software Development
Classifier: Topic :: System :: Systems Administration
Requires-Dist: prettytable
Requires-Dist: pyOpenSSL (>=0.15.1)
Requires-Dist: pytz
